{"repo_root": ".", "tool_version": "0.1.0.dev789", "schema_version": "1.0", "snapshot_count": 1, "latest_snapshot": "0540ba1d87621453a27ad9b1664b4ec0e2f2ea88d42b741c93f1f210d69ce570", "latest_created": "2026-03-13T12:53:18.300871+00:00", "db_exists": true, "summary": {"snapshot_id": "0540ba1d87621453a27ad9b1664b4ec0e2f2ea88d42b741c93f1f210d69ce570", "created_at": "2026-03-13T12:53:18.300871+00:00", "build_total_seconds": 166.982051, "build_wall_seconds": 171.194303, "build_phase_timings": {"build_structural_index": 45.62868805699691, "compute_build_fingerprint": 0.3792136350093642, "derive_call_artifacts": 49.55949262699869, "discover_files": 1.2993856510001933, "prepare_callsite_pairs": 7.622836698996252, "prepare_snapshots": 0.7959805040009087, "rebuild_graph_index": 3.579585126004531, "rebuild_graph_rollups": 3.5892463519994635, "register_modules": 1.4826930920098675, "write_callsite_pairs": 12.603471395006636}, "artifact_db_available": true, "callsite_pairs_semantics": "deduplicated_persisted_in_scope_candidate_pairs", "finalized_call_edges_semantics": "deduplicated_graph_edges_derived_from_callsite_pairs", "languages": [{"language": "java", "files": 3243, "nodes": 64129, "edges": 67212, "callsite_pairs": {"count": 36099}, "finalized_call_edges": {"count": 36064}, "call_site_funnel": {"observed_syntactic_callsites": 36639, "filtered_pre_persist": 1266, "persisted_callsites": 35373, "persisted_accepted": 34844, "persisted_dropped": 529, "record_drops": {"no_resolved_callees": 836}, "conservation_ok": true}, "persisted_callsite_pair_expansion": {"persisted_callsites": 35373, "persisted_callsites_with_zero_pairs": 176, "persisted_callsites_with_one_pair": 34844, "persisted_callsites_with_multiple_pairs": 353, "pair_expansion_factor": 1.02052412857264, "multi_pair_share": 0.009979362790829163, "max_pairs_for_single_persisted_callsite": 34}, "filtered_pre_persist_buckets": {"no_in_repo_candidate_terminal": 0, "no_in_repo_candidate_qualified": 1266, "accepted_outside_in_repo": 0, "invalid_observation_shape": 0}, "callsite_pairs_by_scope": {"non_tests": {"count": 24194}, "tests": {"count": 11905}}, "finalized_call_edges_by_scope": {"non_tests": {"count": 24159}, "tests": {"count": 11905}}, "call_site_funnel_by_scope": {"non_tests": {"observed_syntactic_callsites": 23556, "filtered_pre_persist": 177, "persisted_callsites": 23379, "persisted_accepted": 22939, "persisted_dropped": 440, "record_drops": {"no_resolved_callees": 193}, "conservation_ok": true}, "tests": {"observed_syntactic_callsites": 13083, "filtered_pre_persist": 1089, "persisted_callsites": 11994, "persisted_accepted": 11905, "persisted_dropped": 89, "record_drops": {"no_resolved_callees": 643}, "conservation_ok": true}}, "persisted_callsite_pair_expansion_by_scope": {"non_tests": {"persisted_callsites": 23379, "persisted_callsites_with_zero_pairs": 87, "persisted_callsites_with_one_pair": 22939, "persisted_callsites_with_multiple_pairs": 353, "pair_expansion_factor": 1.034860344753839, "multi_pair_share": 0.01509902048847256, "max_pairs_for_single_persisted_callsite": 34}, "tests": {"persisted_callsites": 11994, "persisted_callsites_with_zero_pairs": 89, "persisted_callsites_with_one_pair": 11905, "persisted_callsites_with_multiple_pairs": 0, "pair_expansion_factor": 0.9925796231449058, "multi_pair_share": 0.0, "max_pairs_for_single_persisted_callsite": 1}}, "structural_density": {"files": 3243, "discovered_files": 3243, "nodes": 64129, "eligible_callsites": 36099, "nodes_per_file": 19.77459142769041, "eligible_callsites_per_file": 11.131359851988899, "low_node_files_leq_1": 144, "low_node_file_ratio": 0.04440333024976873, "inferred_zero_node_files": 0, "inferred_zero_node_ratio": 0.0, "top_low_node_dirs": [{"name": "guava/src", "count": 48}, {"name": "android/guava", "count": 47}, {"name": "android/guava-testlib", "count": 13}, {"name": "guava-testlib/src", "count": 12}, {"name": "android/guava-tests", "count": 10}], "inflation_warning": false, "warnings": [], "zero_node_files_observed": 0, "zero_node_files_note": "Not observable from indexed files; files without nodes are not materialized in node_instances."}, "filtered_pre_persist_buckets_by_scope": {"non_tests": {"no_in_repo_candidate_terminal": 0, "no_in_repo_candidate_qualified": 0, "accepted_outside_in_repo": 0, "invalid_observation_shape": 0}, "tests": {"no_in_repo_candidate_terminal": 0, "no_in_repo_candidate_qualified": 0, "accepted_outside_in_repo": 0, "invalid_observation_shape": 0}}}, {"language": "javascript", "files": 2, "nodes": 2, "edges": 0, "callsite_pairs": {"count": 0}, "finalized_call_edges": {"count": 0}, "call_site_funnel": {"observed_syntactic_callsites": 0, "filtered_pre_persist": 0, "persisted_callsites": 0, "persisted_accepted": 0, "persisted_dropped": 0, "record_drops": {}, "conservation_ok": true}, "persisted_callsite_pair_expansion": {"persisted_callsites": 0, "persisted_callsites_with_zero_pairs": 0, "persisted_callsites_with_one_pair": 0, "persisted_callsites_with_multiple_pairs": 0, "pair_expansion_factor": null, "multi_pair_share": null, "max_pairs_for_single_persisted_callsite": 0}, "callsite_pairs_by_scope": {"non_tests": {"count": 0}, "tests": {"count": 0}}, "finalized_call_edges_by_scope": {"non_tests": {"count": 0}, "tests": {"count": 0}}, "call_site_funnel_by_scope": null, "persisted_callsite_pair_expansion_by_scope": null, "structural_density": {"files": 2, "discovered_files": 2, "nodes": 2, "eligible_callsites": 0, "nodes_per_file": 1.0, "eligible_callsites_per_file": 0.0, "low_node_files_leq_1": 2, "low_node_file_ratio": 1.0, "inferred_zero_node_files": 0, "inferred_zero_node_ratio": 0.0, "top_low_node_dirs": [{"name": "guava-gwt/src-super", "count": 2}], "inflation_warning": false, "warnings": ["low_node_file_ratio_high"], "zero_node_files_observed": 0, "zero_node_files_note": "Not observable from indexed files; files without nodes are not materialized in node_instances."}, "filtered_pre_persist_buckets": {"no_in_repo_candidate_terminal": 0, "no_in_repo_candidate_qualified": 0, "accepted_outside_in_repo": 0, "invalid_observation_shape": 0}, "filtered_pre_persist_buckets_by_scope": {"non_tests": {"no_in_repo_candidate_terminal": 0, "no_in_repo_candidate_qualified": 0, "accepted_outside_in_repo": 0, "invalid_observation_shape": 0}, "tests": {"no_in_repo_candidate_terminal": 0, "no_in_repo_candidate_qualified": 0, "accepted_outside_in_repo": 0, "invalid_observation_shape": 0}}}], "totals": {"files": 3245, "nodes": 64131, "edges": 67212, "callsite_pairs": {"count": 36099}, "finalized_call_edges": {"count": 36064}, "call_site_funnel": {"observed_syntactic_callsites": 36639, "filtered_pre_persist": 1266, "persisted_callsites": 35373, "persisted_accepted": 34844, "persisted_dropped": 529, "record_drops": {"no_resolved_callees": 836}, "conservation_ok": true}, "persisted_callsite_pair_expansion": {"persisted_callsites": 35373, "persisted_callsites_with_zero_pairs": 176, "persisted_callsites_with_one_pair": 34844, "persisted_callsites_with_multiple_pairs": 353, "pair_expansion_factor": 1.02052412857264, "multi_pair_share": 0.009979362790829163, "max_pairs_for_single_persisted_callsite": 34}, "callsite_pairs_by_scope": {"non_tests": {"count": 24194}, "tests": {"count": 11905}}, "finalized_call_edges_by_scope": {"non_tests": {"count": 24159}, "tests": {"count": 11905}}, "call_site_funnel_by_scope": {"non_tests": {"observed_syntactic_callsites": 23556, "filtered_pre_persist": 177, "persisted_callsites": 23379, "persisted_accepted": 22939, "persisted_dropped": 440, "record_drops": {"no_resolved_callees": 193}, "conservation_ok": true}, "tests": {"observed_syntactic_callsites": 13083, "filtered_pre_persist": 1089, "persisted_callsites": 11994, "persisted_accepted": 11905, "persisted_dropped": 89, "record_drops": {"no_resolved_callees": 643}, "conservation_ok": true}}, "persisted_callsite_pair_expansion_by_scope": {"non_tests": {"persisted_callsites": 23379, "persisted_callsites_with_zero_pairs": 87, "persisted_callsites_with_one_pair": 22939, "persisted_callsites_with_multiple_pairs": 353, "pair_expansion_factor": 1.034860344753839, "multi_pair_share": 0.01509902048847256, "max_pairs_for_single_persisted_callsite": 34}, "tests": {"persisted_callsites": 11994, "persisted_callsites_with_zero_pairs": 89, "persisted_callsites_with_one_pair": 11905, "persisted_callsites_with_multiple_pairs": 0, "pair_expansion_factor": 0.9925796231449058, "multi_pair_share": 0.0, "max_pairs_for_single_persisted_callsite": 1}}, "filtered_pre_persist_buckets": {"no_in_repo_candidate_terminal": 0, "no_in_repo_candidate_qualified": 1266, "accepted_outside_in_repo": 0, "invalid_observation_shape": 0}, "structural_density": {"files": 3245, "discovered_files": 3245, "nodes": 64131, "eligible_callsites": 36099, "nodes_per_file": 19.76302003081664, "eligible_callsites_per_file": 11.124499229583975, "low_node_files_leq_1": 146, "low_node_file_ratio": 0.04499229583975347, "inferred_zero_node_files": 0, "inferred_zero_node_ratio": 0.0, "top_low_node_dirs": [{"name": "guava/src", "count": 48}, {"name": "android/guava", "count": 47}, {"name": "android/guava-testlib", "count": 13}, {"name": "guava-testlib/src", "count": 12}, {"name": "android/guava-tests", "count": 10}], "inflation_warning": false, "warnings": [], "zero_node_files_observed": 0, "zero_node_files_note": "Not observable from indexed files; files without nodes are not materialized in node_instances."}, "filtered_pre_persist_buckets_by_scope": {"non_tests": {"no_in_repo_candidate_terminal": 0, "no_in_repo_candidate_qualified": 0, "accepted_outside_in_repo": 0, "invalid_observation_shape": 0}, "tests": {"no_in_repo_candidate_terminal": 0, "no_in_repo_candidate_qualified": 0, "accepted_outside_in_repo": 0, "invalid_observation_shape": 0}}}}, "detailed": true, "status_report_version": 1}
