{
  "diagnostic_kind": "pre_persist_filter_best_effort",
  "diagnostic_mode": true,
  "report": {
    "artifact_db_available": true,
    "labels": {
      "fields": {
        "accepted_outside_in_repo": "Accepted Outside In-Repo",
        "build_phase_timings": "Build Phase Timing",
        "build_total_seconds": "Build Total Time",
        "build_wall_seconds": "Build Wall Time",
        "callsite_pairs": "Callsite Pairs",
        "edges": "Edges",
        "files": "Files",
        "filtered_pre_persist": "Filtered Pre-Persist",
        "finalized_call_edges": "Finalized Call Edges",
        "invalid_observation_shape": "Invalid Observation Shape",
        "likely_dynamic_dispatch_or_indirect": "Likely Dynamic Dispatch Or Indirect",
        "likely_external_dependency": "Likely External Dependency",
        "likely_parser_extraction_gap": "Likely Parser Extraction Gap",
        "likely_standard_library_or_builtin": "Likely Standard Library Or Builtin",
        "likely_unindexed_symbol": "Likely Unindexed Symbol",
        "no_in_repo_candidate": "No In-Repo Candidate",
        "nodes": "Nodes",
        "observed_syntactic_callsites": "Observed Syntactic Callsites",
        "persisted_accepted": "Persisted Accepted",
        "persisted_callsites": "Persisted Callsites",
        "persisted_dropped": "Persisted Dropped",
        "unclassified_no_in_repo_candidate": "Unclassified No In-Repo Candidate"
      },
      "phases": {
        "build_structural_index": "Build Structural Index",
        "compute_build_fingerprint": "Compute Build Fingerprint",
        "derive_call_artifacts": "Extract Call Observations",
        "diagnostic_classification": "Diagnostic Classification",
        "discover_files": "Discover Files",
        "prepare_callsite_pairs": "Prepare Callsite Pairs",
        "prepare_snapshots": "Prepare Snapshots",
        "rebuild_graph_index": "Rebuild Call Graph Index",
        "rebuild_graph_rollups": "Rebuild Graph Rollups",
        "register_modules": "Register Modules",
        "write_callsite_pairs": "Write Callsite Pairs"
      },
      "scopes": {
        "non_tests": "Non-Tests",
        "tests": "Tests"
      },
      "sections": {
        "call_materialization": "Call Materialization",
        "callsites": "Callsites",
        "pre_persist_filter": "Pre-Persist Filter",
        "structure": "Structure",
        "timing": "Timing"
      }
    },
    "languages": {
      "javascript": {
        "call_materialization": {
          "callsite_pairs": 3349,
          "finalized_call_edges": 3328
        },
        "callsites": {
          "filtered_pre_persist": 132,
          "observed_syntactic_callsites": 3484,
          "persisted_accepted": 3349,
          "persisted_callsites": 3352,
          "persisted_dropped": 3
        },
        "pre_persist_filter": {
          "accepted_outside_in_repo": 0,
          "invalid_observation_shape": 0,
          "likely_dynamic_dispatch_or_indirect": 0,
          "likely_external_dependency": 0,
          "likely_parser_extraction_gap": 32,
          "likely_standard_library_or_builtin": 0,
          "likely_unindexed_symbol": 100,
          "unclassified_no_in_repo_candidate": 0
        },
        "structure": {
          "edges": 15347,
          "files": 8615,
          "nodes": 15627
        }
      },
      "typescript": {
        "call_materialization": {
          "callsite_pairs": 12,
          "finalized_call_edges": 12
        },
        "callsites": {
          "filtered_pre_persist": 0,
          "observed_syntactic_callsites": 12,
          "persisted_accepted": 12,
          "persisted_callsites": 12,
          "persisted_dropped": 0
        },
        "pre_persist_filter": {
          "accepted_outside_in_repo": 0,
          "invalid_observation_shape": 0,
          "likely_dynamic_dispatch_or_indirect": 0,
          "likely_external_dependency": 0,
          "likely_parser_extraction_gap": 0,
          "likely_standard_library_or_builtin": 0,
          "likely_unindexed_symbol": 0,
          "unclassified_no_in_repo_candidate": 0
        },
        "structure": {
          "edges": 116,
          "files": 88,
          "nodes": 188
        }
      }
    },
    "scopes": {
      "non_tests": {
        "call_materialization": {
          "callsite_pairs": 2958,
          "finalized_call_edges": 2937
        },
        "callsites": {
          "filtered_pre_persist": 126,
          "observed_syntactic_callsites": 3087,
          "persisted_accepted": 2958,
          "persisted_callsites": 2961,
          "persisted_dropped": 3
        },
        "pre_persist_filter": {
          "accepted_outside_in_repo": 0,
          "invalid_observation_shape": 0,
          "likely_dynamic_dispatch_or_indirect": 0,
          "likely_external_dependency": 0,
          "likely_parser_extraction_gap": 31,
          "likely_standard_library_or_builtin": 0,
          "likely_unindexed_symbol": 95,
          "unclassified_no_in_repo_candidate": 0
        },
        "structure": {
          "edges": 10063,
          "files": 1160,
          "nodes": 6182
        }
      },
      "tests": {
        "call_materialization": {
          "callsite_pairs": 403,
          "finalized_call_edges": 403
        },
        "callsites": {
          "filtered_pre_persist": 6,
          "observed_syntactic_callsites": 409,
          "persisted_accepted": 403,
          "persisted_callsites": 403,
          "persisted_dropped": 0
        },
        "pre_persist_filter": {
          "accepted_outside_in_repo": 0,
          "invalid_observation_shape": 0,
          "likely_dynamic_dispatch_or_indirect": 0,
          "likely_external_dependency": 0,
          "likely_parser_extraction_gap": 1,
          "likely_standard_library_or_builtin": 0,
          "likely_unindexed_symbol": 5,
          "unclassified_no_in_repo_candidate": 0
        },
        "structure": {
          "edges": 5400,
          "files": 7543,
          "nodes": 9633
        }
      }
    },
    "timing": {
      "build_phase_timings": {
        "build_structural_index": 14.83417697600089,
        "compute_build_fingerprint": 0.4348785150068579,
        "derive_call_artifacts": 13.478943552006967,
        "diagnostic_classification": 0.1148576760024298,
        "discover_files": 2.0453401039994787,
        "prepare_callsite_pairs": 0.14880410599289462,
        "prepare_snapshots": 1.6233901139930822,
        "rebuild_graph_index": 0.3218508470017696,
        "rebuild_graph_rollups": 0.34652141699916683,
        "register_modules": 3.134690322985989,
        "write_callsite_pairs": 0.10285206900152843
      },
      "build_total_seconds": 47.392222,
      "build_wall_seconds": null
    },
    "totals": {
      "call_materialization": {
        "callsite_pairs": 3361,
        "finalized_call_edges": 3340
      },
      "callsites": {
        "filtered_pre_persist": 132,
        "observed_syntactic_callsites": 3496,
        "persisted_accepted": 3361,
        "persisted_callsites": 3364,
        "persisted_dropped": 3
      },
      "pre_persist_filter": {
        "accepted_outside_in_repo": 0,
        "invalid_observation_shape": 0,
        "likely_dynamic_dispatch_or_indirect": 0,
        "likely_external_dependency": 0,
        "likely_parser_extraction_gap": 32,
        "likely_standard_library_or_builtin": 0,
        "likely_unindexed_symbol": 100,
        "unclassified_no_in_repo_candidate": 0
      },
      "structure": {
        "edges": 15463,
        "files": 8703,
        "nodes": 15815
      }
    }
  }
}
